{
  "id": "",
  "name": "",
  "font_family": "iconfont",
  "css_prefix_text": "icon-",
  "description": "",
  "glyphs": [
    {
      "icon_id": "7425",
      "name": "暂停",
      "font_class": "zanting",
      "unicode": "f0299",
      "unicode_decimal": 983705
    },
    {
      "icon_id": "688097",
      "name": "上一首 上一个",
      "font_class": "shangyishoushangyige",
      "unicode": "e78a",
      "unicode_decimal": 59274
    },
    {
      "icon_id": "688128",
      "name": "下一个 下一首",
      "font_class": "xiayigexiayishou",
      "unicode": "e7a5",
      "unicode_decimal": 59301
    },
    {
      "icon_id": "1311984",
      "name": "单曲循环",
      "font_class": "danquxunhuan",
      "unicode": "e63e",
      "unicode_decimal": 58942
    },
    {
      "icon_id": "1488899",
      "name": "列表循环",
      "font_class": "liebiaoxunhuan",
      "unicode": "e609",
      "unicode_decimal": 58889
    },
    {
      "icon_id": "2076215",
      "name": "音量",
      "font_class": "yinliang",
      "unicode": "e87a",
      "unicode_decimal": 59514
    },
    {
      "icon_id": "2076319",
      "name": "播放",
      "font_class": "bofang",
      "unicode": "e8a3",
      "unicode_decimal": 59555
    },
    {
      "icon_id": "7417088",
      "name": "随机播放",
      "font_class": "suijibofang",
      "unicode": "e603",
      "unicode_decimal": 58883
    }
  ]
}
